copyright_cli/__init__.py
copyright_cli/cli.py
copyright_cli/cli_parsers/__init__.py
copyright_cli/cli_parsers/AddCommandParser.py
copyright_cli/cli_parsers/ArgumentParser.py
copyright_cli/cli_parsers/DebugParser.py
copyright_cli/copyright.py
copyright_cli/internal/__init__.py
copyright_cli/internal/Configuration.py
copyright_cli/internal/CopyrightInfo.py
copyright_cli/internal/FileProcessor.py
copyright_cli/internal/FileSearch.py
copyright_cli-0.1.0rc3.dist-info/entry_points.txt
copyright_cli-0.1.0rc3.dist-info/METADATA
copyright_cli-0.1.0rc3.dist-info/WHEEL
copyright_cli-0.1.0rc3.dist-info/RECORD
