Metadata-Version: 2.1
Name: copyright-cli
Version: 0.1.0rc3
Summary: 
Author: Nicholas Johnson
Author-email: nicholas.m.j@gmail.com
Requires-Python: >=3.9,<4.0
Classifier: Programming Language :: Python :: 3
Classifier: Programming Language :: Python :: 3.9
Classifier: Programming Language :: Python :: 3.10
Classifier: Programming Language :: Python :: 3.11
Requires-Dist: tomlkit (>=0.11.6,<0.12.0)
